filedgr_xrpl_cli/__init__.py
filedgr_xrpl_cli/__main__.py
filedgr_xrpl_cli/dto/__init__.py
filedgr_xrpl_cli/dto/network.py
filedgr_xrpl_cli/my_io/__init__.py
filedgr_xrpl_cli/my_io/file_io.py
filedgr_xrpl_cli/my_xrpl/__init__.py
filedgr_xrpl_cli/my_xrpl/connection.py
filedgr_xrpl_cli/my_xrpl/tx.py
filedgr_xrpl_cli/my_xrpl/wallet.py
filedgr_xrpl_cli/nft_utils/__init__.py
filedgr_xrpl_cli/nft_utils/id_gen.py
filedgr_xrpl_cli-0.0.1b0.dist-info/LICENSE
filedgr_xrpl_cli-0.0.1b0.dist-info/METADATA
filedgr_xrpl_cli-0.0.1b0.dist-info/WHEEL
filedgr_xrpl_cli-0.0.1b0.dist-info/entry_points.txt
filedgr_xrpl_cli-0.0.1b0.dist-info/top_level.txt
filedgr_xrpl_cli-0.0.1b0.dist-info/RECORD
